<?xml version="1.0" encoding="UTF-8" ?>
<xml>
	<better>
		<omega mean="0.02315882" deviation="0.19315577" sum="24597.44220283" squareSum="40196.44369445" numSamples="1062120" />
		<inconsistency mean="0.00609821" deviation="0.02664706" sum="6477.02572914" squareSum="793.67344484" numSamples="1062120" />
		<icSize mean="7.01318401" deviation="11.47289121" sum="7448843" squareSum="192044023" numSamples="1062120" />
		<entitiesInInconsistentArea mean="76.51864479" deviation="188.78325413" sum="81271983" squareSum="4.4071841e10" numSamples="1062120" />
		<entitiesInSDS mean="1021.45670734" deviation="32.48086689" sum="1084909598" squareSum="1.10930873e12" numSamples="1062120" />
		<inconsistencyProbability mean="0.27479748" deviation="0.34932864" sum="291867.89811896" squareSum="209815.59463368" numSamples="1062120" />
		<inconsistentEntitiesOutsideIC mean="0" deviation="0" sum="0" squareSum="0" numSamples="1062120" />
		<missingEntities mean="12.49702576" deviation="43.40531473" sum="13273341" squareSum="2.16693404e9" numSamples="1062120" />
		<overAccountedEntities mean="7.10025609" deviation="27.22435808" sum="7541324" squareSum="840752216" numSamples="1062120" />
	</better>
	<worse>
		<omega mean="0.04805966" deviation="0.29764429" sum="51045.12403961" squareSum="96548.67558743" numSamples="1062120" />
		<inconsistency mean="0.0105859" deviation="0.03796328" sum="11243.49328234" squareSum="1649.76100503" numSamples="1062120" />
		<icSize mean="12.91658758" deviation="13.87796226" sum="13718966" squareSum="381764240" numSamples="1062120" />
		<entitiesInInconsistentArea mean="76.51864479" deviation="188.78325413" sum="81271983" squareSum="4.4071841e10" numSamples="1062120" />
		<entitiesInSDS mean="1021.45670734" deviation="32.48086689" sum="1084909598" squareSum="1.10930873e12" numSamples="1062120" />
		<inconsistencyProbability mean="0.36396829" deviation="0.41071046" sum="386578.00022816" squareSum="319863.80657431" numSamples="1062120" />
		<inconsistentEntitiesOutsideIC mean="0" deviation="0" sum="0" squareSum="0" numSamples="1062120" />
		<missingEntities mean="16.89067808" deviation="55.12272883" sum="17939927" squareSum="3.53028533e9" numSamples="1062120" />
		<overAccountedEntities mean="19.57058524" deviation="42.64040267" sum="20786310" squareSum="2.33795102e9" numSamples="1062120" />
	</worse>
	<capture class="Binary_ExPC">
		<omega relative="0.30324" mean="0.03070969" deviation="0.24238087" sum="32617.37255785" squareSum="63399.61330005" numSamples="1062120" />
		<inconsistency relative="0.17549" mean="0.00688577" deviation="0.02948929" sum="7313.51498294" squareSum="973.99798376" numSamples="1062120" />
		<icSize relative="-0.37515" mean="4.7985463" deviation="11.82099154" sum="5096632" squareSum="172872656" numSamples="1062120" />
		<entitiesInInconsistentArea relative="-INF" mean="76.51864479" deviation="188.78325413" sum="81271983" squareSum="4.4071841e10" numSamples="1062120" />
		<entitiesInSDS relative="-INF" mean="489.33345761" deviation="511.08786359" sum="519730852" squareSum="5.31758914e11" numSamples="1062120" />
		<inconsistencyProbability relative="0.23281" mean="0.29555697" deviation="0.36548015" sum="313916.96837606" squareSum="234653.81561447" numSamples="1062120" />
		<inconsistentEntitiesOutsideIC relative="+INF" mean="0.03519368" deviation="0.09769048" sum="37379.91628798" squareSum="11451.80488335" numSamples="1062120" />
		<missingEntities relative="0.28036" mean="13.72881125" deviation="47.93351098" sum="14581645" squareSum="2.64053837e9" numSamples="1062120" />
		<overAccountedEntities relative="0.02148" mean="7.36817591" deviation="31.28678682" sum="7825887" squareSum="1097332513" numSamples="1062120" />
	</capture>
	<capture class="Plane (-0.00575, 0.00748, 0.035)_Ex">
		<omega relative="0.4926" mean="0.03542495" deviation="0.25293082" sum="37625.54656472" squareSum="69280.94565142" numSamples="1062120" />
		<inconsistency relative="0.43388" mean="0.00804532" deviation="0.03211456" sum="8545.09753179" squareSum="1164.16022802" numSamples="1062120" />
		<icSize relative="-0.37515" mean="4.7985463" deviation="11.82099154" sum="5096632" squareSum="172872656" numSamples="1062120" />
		<entitiesInInconsistentArea relative="-INF" mean="76.51864479" deviation="188.78325413" sum="81271983" squareSum="4.4071841e10" numSamples="1062120" />
		<entitiesInSDS relative="-INF" mean="489.33345761" deviation="511.08786359" sum="519730852" squareSum="5.31758914e11" numSamples="1062120" />
		<inconsistencyProbability relative="0.4972" mean="0.31913335" deviation="0.38367477" sum="338957.91279314" squareSum="264523.56160827" numSamples="1062120" />
		<inconsistentEntitiesOutsideIC relative="+INF" mean="0.03519368" deviation="0.09769048" sum="37379.91628798" squareSum="11451.80488335" numSamples="1062120" />
		<missingEntities relative="0.65087" mean="15.35673653" deviation="51.73605878" sum="16310697" squareSum="3.09337048e9" numSamples="1062120" />
		<overAccountedEntities relative="0.07692" mean="8.05943679" deviation="32.89823903" sum="8560089" squareSum="1218515739" numSamples="1062120" />
	</capture>
	<capture class="Plane (-0.00575, 0.00748, 0.035)_ExPC">
		<omega relative="0.59524" mean="0.0379808" deviation="0.25695829" sum="40340.16486262" squareSum="71661.34879599" numSamples="1062120" />
		<inconsistency relative="0.45378" mean="0.00813465" deviation="0.0323295" sum="8639.97538891" squareSum="1180.40707108" numSamples="1062120" />
		<icSize relative="-0.37515" mean="4.7985463" deviation="11.82099154" sum="5096632" squareSum="172872656" numSamples="1062120" />
		<entitiesInInconsistentArea relative="-INF" mean="76.51864479" deviation="188.78325413" sum="81271983" squareSum="4.4071841e10" numSamples="1062120" />
		<entitiesInSDS relative="-INF" mean="489.33345761" deviation="511.08786359" sum="519730852" squareSum="5.31758914e11" numSamples="1062120" />
		<inconsistencyProbability relative="0.4972" mean="0.31913335" deviation="0.38367477" sum="338957.91279314" squareSum="264523.56160827" numSamples="1062120" />
		<inconsistentEntitiesOutsideIC relative="+INF" mean="0.03519368" deviation="0.09769048" sum="37379.91628798" squareSum="11451.80488335" numSamples="1062120" />
		<missingEntities relative="0.50228" mean="14.70388845" deviation="49.80380242" sum="15617294" squareSum="2.8641373e9" numSamples="1062120" />
		<overAccountedEntities relative="0.1585" mean="9.07682089" deviation="35.2313808" sum="9640673" squareSum="1405863317" numSamples="1062120" />
	</capture>
	<capture class="Orthographic (extent&gt;depth)_ExPC">
		<omega relative="0.36826" mean="0.0323288" deviation="0.23728721" sum="34337.0655119" squareSum="60912.97865706" numSamples="1062120" />
		<inconsistency relative="0.23589" mean="0.00715681" deviation="0.02988664" sum="7601.39186684" squareSum="1003.09910596" numSamples="1062120" />
		<icSize relative="-0.37515" mean="4.7985463" deviation="11.82099154" sum="5096632" squareSum="172872656" numSamples="1062120" />
		<entitiesInInconsistentArea relative="-INF" mean="76.51864479" deviation="188.78325413" sum="81271983" squareSum="4.4071841e10" numSamples="1062120" />
		<entitiesInSDS relative="-INF" mean="489.33345761" deviation="511.08786359" sum="519730852" squareSum="5.31758914e11" numSamples="1062120" />
		<inconsistencyProbability relative="0.22019" mean="0.29443174" deviation="0.36653215" sum="312721.83938233" squareSum="234766.61716136" numSamples="1062120" />
		<inconsistentEntitiesOutsideIC relative="+INF" mean="0.03519368" deviation="0.09769048" sum="37379.91628798" squareSum="11451.80488335" numSamples="1062120" />
		<missingEntities relative="0.1542" mean="13.17451889" deviation="46.11872839" sum="13992920" squareSum="2.44341243e9" numSamples="1062120" />
		<overAccountedEntities relative="0.09725" mean="8.31303807" deviation="33.60748863" sum="8829444" squareSum="1273025056" numSamples="1062120" />
	</capture>
	<capture class="Depth">
		<omega relative="0.20955" mean="0.02837682" deviation="0.21688213" sum="30139.5871687" squareSum="50815.11415193" numSamples="1062120" />
		<inconsistency relative="0.19047" mean="0.00695297" deviation="0.02844148" sum="7384.88854614" squareSum="910.51480209" numSamples="1062120" />
		<icSize relative="-0.37515" mean="4.7985463" deviation="11.82099154" sum="5096632" squareSum="172872656" numSamples="1062120" />
		<entitiesInInconsistentArea relative="-INF" mean="76.51864479" deviation="188.78325413" sum="81271983" squareSum="4.4071841e10" numSamples="1062120" />
		<entitiesInSDS relative="-INF" mean="489.33345761" deviation="511.08786359" sum="519730852" squareSum="5.31758914e11" numSamples="1062120" />
		<inconsistencyProbability relative="0.31496" mean="0.30288269" deviation="0.36950939" sum="321697.7678638" squareSum="242455.5689144" numSamples="1062120" />
		<inconsistentEntitiesOutsideIC relative="+INF" mean="0.03519368" deviation="0.09769048" sum="37379.91628798" squareSum="11451.80488335" numSamples="1062120" />
		<missingEntities relative="0.09789" mean="12.92710993" deviation="44.6376663" sum="13730142" squareSum="2.29378773e9" numSamples="1062120" />
		<overAccountedEntities relative="0.04808" mean="7.69979569" deviation="31.77266141" sum="8178107" squareSum="1135182031" numSamples="1062120" />
	</capture>
	<capture class="Depth_ExPC">
		<omega relative="0.13862" mean="0.02661064" deviation="0.21563796" sum="28263.69380547" squareSum="50140.40990263" numSamples="1062120" />
		<inconsistency relative="0.09539" mean="0.0065263" deviation="0.02800366" sum="6931.71245067" squareSum="878.1582952" numSamples="1062120" />
		<icSize relative="-0.37515" mean="4.7985463" deviation="11.82099154" sum="5096632" squareSum="172872656" numSamples="1062120" />
		<entitiesInInconsistentArea relative="-INF" mean="76.51864479" deviation="188.78325413" sum="81271983" squareSum="4.4071841e10" numSamples="1062120" />
		<entitiesInSDS relative="-INF" mean="489.33345761" deviation="511.08786359" sum="519730852" squareSum="5.31758914e11" numSamples="1062120" />
		<inconsistencyProbability relative="0.20704" mean="0.29325918" deviation="0.36429413" sum="311476.43587001" squareSum="232297.49070888" numSamples="1062120" />
		<inconsistentEntitiesOutsideIC relative="+INF" mean="0.03519368" deviation="0.09769048" sum="37379.91628798" squareSum="11451.80488335" numSamples="1062120" />
		<missingEntities relative="0.23929" mean="13.54836647" deviation="45.80080758" sum="14389991" squareSum="2.42298484e9" numSamples="1062120" />
		<overAccountedEntities relative="-0.02732" mean="6.75962509" deviation="29.5966855" sum="7179533" squareSum="978909615" numSamples="1062120" />
	</capture>
	<capture class="Orthographic (extent&gt;depth)">
		<omega relative="0.35649" mean="0.03203578" deviation="0.23028012" sum="34025.8404632" squareSum="57413.13670975" numSamples="1062120" />
		<inconsistency relative="0.29403" mean="0.00741774" deviation="0.02982284" sum="7878.52805272" squareSum="1003.09257746" numSamples="1062120" />
		<icSize relative="-0.37515" mean="4.7985463" deviation="11.82099154" sum="5096632" squareSum="172872656" numSamples="1062120" />
		<entitiesInInconsistentArea relative="-INF" mean="76.51864479" deviation="188.78325413" sum="81271983" squareSum="4.4071841e10" numSamples="1062120" />
		<entitiesInSDS relative="-INF" mean="489.33345761" deviation="511.08786359" sum="519730852" squareSum="5.31758914e11" numSamples="1062120" />
		<inconsistencyProbability relative="0.34092" mean="0.3051972" deviation="0.37259416" sum="324156.05045071" squareSum="246381.82536478" numSamples="1062120" />
		<inconsistentEntitiesOutsideIC relative="+INF" mean="0.03519368" deviation="0.09769048" sum="37379.91628798" squareSum="11451.80488335" numSamples="1062120" />
		<missingEntities relative="0.12155" mean="13.03109253" deviation="45.78681513" sum="13840584" squareSum="2.40702075e9" numSamples="1062120" />
		<overAccountedEntities relative="0.11911" mean="8.58563157" deviation="33.78068166" sum="9118971" squareSum="1290313851" numSamples="1062120" />
	</capture>
	<capture class="Orthographic (extent&gt;depth)_Ex">
		<omega relative="0.33292" mean="0.03144876" deviation="0.23685499" sum="33402.36123553" squareSum="60635.69849864" numSamples="1062120" />
		<inconsistency relative="0.2296" mean="0.0071286" deviation="0.02982269" sum="7571.42793252" squareSum="998.61573541" numSamples="1062120" />
		<icSize relative="-0.37515" mean="4.7985463" deviation="11.82099154" sum="5096632" squareSum="172872656" numSamples="1062120" />
		<entitiesInInconsistentArea relative="-INF" mean="76.51864479" deviation="188.78325413" sum="81271983" squareSum="4.4071841e10" numSamples="1062120" />
		<entitiesInSDS relative="-INF" mean="489.33345761" deviation="511.08786359" sum="519730852" squareSum="5.31758914e11" numSamples="1062120" />
		<inconsistencyProbability relative="0.22019" mean="0.29443174" deviation="0.36653215" sum="312721.83938233" squareSum="234766.61716136" numSamples="1062120" />
		<inconsistentEntitiesOutsideIC relative="+INF" mean="0.03519368" deviation="0.09769048" sum="37379.91628798" squareSum="11451.80488335" numSamples="1062120" />
		<missingEntities relative="0.20745" mean="13.40848115" deviation="46.93909816" sum="14241416" squareSum="2.53110238e9" numSamples="1062120" />
		<overAccountedEntities relative="0.07089" mean="7.98433887" deviation="32.88416632" sum="8480326" squareSum="1216252796" numSamples="1062120" />
	</capture>
	<capture class="Binary">
		<omega relative="0.48523" mean="0.03524134" deviation="0.23249386" sum="37430.53697549" squareSum="58730.29251152" numSamples="1062120" />
		<inconsistency relative="0.32817" mean="0.00757092" deviation="0.02984609" sum="8041.22992765" squareSum="1007.00441575" numSamples="1062120" />
		<icSize relative="-0.37515" mean="4.7985463" deviation="11.82099154" sum="5096632" squareSum="172872656" numSamples="1062120" />
		<entitiesInInconsistentArea relative="-INF" mean="76.51864479" deviation="188.78325413" sum="81271983" squareSum="4.4071841e10" numSamples="1062120" />
		<entitiesInSDS relative="-INF" mean="489.33345761" deviation="511.08786359" sum="519730852" squareSum="5.31758914e11" numSamples="1062120" />
		<inconsistencyProbability relative="0.35092" mean="0.30608923" deviation="0.37122557" sum="325103.49385238" squareSum="245879.76139027" numSamples="1062120" />
		<inconsistentEntitiesOutsideIC relative="+INF" mean="0.03519368" deviation="0.09769048" sum="37379.91628798" squareSum="11451.80488335" numSamples="1062120" />
		<missingEntities relative="-0.55713" mean="10.04918088" deviation="31.08075938" sum="10673436" squareSum="1133281658" numSamples="1062120" />
		<overAccountedEntities relative="0.42851" mean="12.44387922" deviation="52.41755263" sum="13216893" squareSum="3.08275015e9" numSamples="1062120" />
	</capture>
	<capture class="Extent">
		<omega relative="0.48433" mean="0.03521914" deviation="0.23918867" sum="37406.95764386" squareSum="62082.62364136" numSamples="1062120" />
		<inconsistency relative="0.35575" mean="0.00769469" deviation="0.03058274" sum="8172.68054743" squareSum="1056.29135321" numSamples="1062120" />
		<icSize relative="-0.37515" mean="4.7985463" deviation="11.82099154" sum="5096632" squareSum="172872656" numSamples="1062120" />
		<entitiesInInconsistentArea relative="-INF" mean="76.51864479" deviation="188.78325413" sum="81271983" squareSum="4.4071841e10" numSamples="1062120" />
		<entitiesInSDS relative="-INF" mean="489.33345761" deviation="511.08786359" sum="519730852" squareSum="5.31758914e11" numSamples="1062120" />
		<inconsistencyProbability relative="0.34852" mean="0.30587562" deviation="0.37305481" sum="324876.6118015" squareSum="247186.95881254" numSamples="1062120" />
		<inconsistentEntitiesOutsideIC relative="+INF" mean="0.03519368" deviation="0.09769048" sum="37379.91628798" squareSum="11451.80488335" numSamples="1062120" />
		<missingEntities relative="-0.18083" mean="11.70252043" deviation="39.0069161" sum="12429481" squareSum="1761513793" numSamples="1062120" />
		<overAccountedEntities relative="0.28152" mean="10.61095451" deviation="44.80979146" sum="11270107" squareSum="2.25223583e9" numSamples="1062120" />
	</capture>
	<capture class="Orthographic (depth&gt;extent)_Ex">
		<omega relative="0.11465" mean="0.02601377" deviation="0.2156579" sum="27629.74010407" squareSum="50116.18024546" numSamples="1062120" />
		<inconsistency relative="0.09096" mean="0.0065064" deviation="0.02797372" sum="6910.57402156" squareSum="876.10273702" numSamples="1062120" />
		<icSize relative="-0.37515" mean="4.7985463" deviation="11.82099154" sum="5096632" squareSum="172872656" numSamples="1062120" />
		<entitiesInInconsistentArea relative="-INF" mean="76.51864479" deviation="188.78325413" sum="81271983" squareSum="4.4071841e10" numSamples="1062120" />
		<entitiesInSDS relative="-INF" mean="489.33345761" deviation="511.08786359" sum="519730852" squareSum="5.31758914e11" numSamples="1062120" />
		<inconsistencyProbability relative="0.19394" mean="0.29209158" deviation="0.3637546" sum="310236.30452319" squareSum="231154.37953452" numSamples="1062120" />
		<inconsistentEntitiesOutsideIC relative="+INF" mean="0.03519368" deviation="0.09769048" sum="37379.91628798" squareSum="11451.80488335" numSamples="1062120" />
		<missingEntities relative="0.25018" mean="13.59624619" deviation="45.95887219" sum="14440845" squareSum="2.4397702e9" numSamples="1062120" />
		<overAccountedEntities relative="-0.04314" mean="6.56227545" deviation="29.26254593" sum="6969924" squareSum="955228300" numSamples="1062120" />
	</capture>
	<capture class="Orthographic (depth&gt;extent)">
		<omega relative="0.20917" mean="0.02836723" deviation="0.21701346" sum="30129.3993246" squareSum="50875.06308125" numSamples="1062120" />
		<inconsistency relative="0.19049" mean="0.00695305" deviation="0.02846085" sum="7384.97254203" squareSum="911.68627358" numSamples="1062120" />
		<icSize relative="-0.37515" mean="4.7985463" deviation="11.82099154" sum="5096632" squareSum="172872656" numSamples="1062120" />
		<entitiesInInconsistentArea relative="-INF" mean="76.51864479" deviation="188.78325413" sum="81271983" squareSum="4.4071841e10" numSamples="1062120" />
		<entitiesInSDS relative="-INF" mean="489.33345761" deviation="511.08786359" sum="519730852" squareSum="5.31758914e11" numSamples="1062120" />
		<inconsistencyProbability relative="0.30973" mean="0.30241674" deviation="0.36944249" sum="321202.8667621" squareSum="242103.49879013" numSamples="1062120" />
		<inconsistentEntitiesOutsideIC relative="+INF" mean="0.03519368" deviation="0.09769048" sum="37379.91628798" squareSum="11451.80488335" numSamples="1062120" />
		<missingEntities relative="0.11172" mean="12.9878912" deviation="44.83098117" sum="13794699" squareSum="2.31383075e9" numSamples="1062120" />
		<overAccountedEntities relative="0.04277" mean="7.63367228" deviation="31.4175759" sum="8107876" squareSum="1110273364" numSamples="1062120" />
	</capture>
	<capture class="Extent_ExPC">
		<omega relative="0.49206" mean="0.0354116" deviation="0.25987098" sum="37611.36634808" squareSum="73059.95066538" numSamples="1062120" />
		<inconsistency relative="0.29897" mean="0.00743989" deviation="0.03122267" sum="7902.05563549" squareSum="1094.20324419" numSamples="1062120" />
		<icSize relative="-0.37515" mean="4.7985463" deviation="11.82099154" sum="5096632" squareSum="172872656" numSamples="1062120" />
		<entitiesInInconsistentArea relative="-INF" mean="76.51864479" deviation="188.78325413" sum="81271983" squareSum="4.4071841e10" numSamples="1062120" />
		<entitiesInSDS relative="-INF" mean="489.33345761" deviation="511.08786359" sum="519730852" squareSum="5.31758914e11" numSamples="1062120" />
		<inconsistencyProbability relative="0.22579" mean="0.29493169" deviation="0.3670778" sum="313252.84995567" squareSum="235504.73259582" numSamples="1062120" />
		<inconsistentEntitiesOutsideIC relative="+INF" mean="0.03519368" deviation="0.09769048" sum="37379.91628798" squareSum="11451.80488335" numSamples="1062120" />
		<missingEntities relative="0.20421" mean="13.39423323" deviation="47.54639248" sum="14226283" squareSum="2.59164176e9" numSamples="1062120" />
		<overAccountedEntities relative="0.12997" mean="8.72099198" deviation="35.31463859" sum="9262740" squareSum="1405375304" numSamples="1062120" />
	</capture>
	<capture class="Binary_Ex">
		<omega relative="0.27764" mean="0.03007219" deviation="0.24231405" sum="31940.27425384" squareSum="63324.05605172" numSamples="1062120" />
		<inconsistency relative="0.17171" mean="0.00686879" deviation="0.02947461" sum="7295.48002913" squareSum="972.83081225" numSamples="1062120" />
		<icSize relative="-0.37515" mean="4.7985463" deviation="11.82099154" sum="5096632" squareSum="172872656" numSamples="1062120" />
		<entitiesInInconsistentArea relative="-INF" mean="76.51864479" deviation="188.78325413" sum="81271983" squareSum="4.4071841e10" numSamples="1062120" />
		<entitiesInSDS relative="-INF" mean="489.33345761" deviation="511.08786359" sum="519730852" squareSum="5.31758914e11" numSamples="1062120" />
		<inconsistencyProbability relative="0.23281" mean="0.29555697" deviation="0.36548015" sum="313916.96837606" squareSum="234653.81561447" numSamples="1062120" />
		<inconsistentEntitiesOutsideIC relative="+INF" mean="0.03519368" deviation="0.09769048" sum="37379.91628798" squareSum="11451.80488335" numSamples="1062120" />
		<missingEntities relative="0.29541" mean="13.79494502" deviation="48.03342083" sum="14651887" squareSum="2.65265535e9" numSamples="1062120" />
		<overAccountedEntities relative="0.01066" mean="7.23319305" deviation="31.18652297" sum="7682519" squareSum="1088586221" numSamples="1062120" />
	</capture>
	<capture class="Extent_Ex">
		<omega relative="0.45358" mean="0.03445343" deviation="0.25916378" sum="36593.6737916" squareSum="72598.98333319" numSamples="1062120" />
		<inconsistency relative="0.29122" mean="0.00740513" deviation="0.03112799" sum="7865.13364963" squareSum="1087.38518802" numSamples="1062120" />
		<icSize relative="-0.37515" mean="4.7985463" deviation="11.82099154" sum="5096632" squareSum="172872656" numSamples="1062120" />
		<entitiesInInconsistentArea relative="-INF" mean="76.51864479" deviation="188.78325413" sum="81271983" squareSum="4.4071841e10" numSamples="1062120" />
		<entitiesInSDS relative="-INF" mean="489.33345761" deviation="511.08786359" sum="519730852" squareSum="5.31758914e11" numSamples="1062120" />
		<inconsistencyProbability relative="0.22579" mean="0.29493169" deviation="0.3670778" sum="313252.84995567" squareSum="235504.73259582" numSamples="1062120" />
		<inconsistentEntitiesOutsideIC relative="+INF" mean="0.03519368" deviation="0.09769048" sum="37379.91628798" squareSum="11451.80488335" numSamples="1062120" />
		<missingEntities relative="0.27566" mean="13.70818363" deviation="48.72749576" sum="14559736" squareSum="2.72145217e9" numSamples="1062120" />
		<overAccountedEntities relative="0.09877" mean="8.33190506" deviation="34.39055729" sum="8849483" squareSum="1329913455" numSamples="1062120" />
	</capture>
	<capture class="Depth_Ex">
		<omega relative="0.114" mean="0.02599746" deviation="0.21552492" sum="27612.42323837" squareSum="50054.37979073" numSamples="1062120" />
		<inconsistency relative="0.09184" mean="0.00651036" deviation="0.02799091" sum="6914.78227365" squareSum="877.17922086" numSamples="1062120" />
		<icSize relative="-0.37515" mean="4.7985463" deviation="11.82099154" sum="5096632" squareSum="172872656" numSamples="1062120" />
		<entitiesInInconsistentArea relative="-INF" mean="76.51864479" deviation="188.78325413" sum="81271983" squareSum="4.4071841e10" numSamples="1062120" />
		<entitiesInSDS relative="-INF" mean="489.33345761" deviation="511.08786359" sum="519730852" squareSum="5.31758914e11" numSamples="1062120" />
		<inconsistencyProbability relative="0.20704" mean="0.29325918" deviation="0.36429413" sum="311476.43587001" squareSum="232297.49070888" numSamples="1062120" />
		<inconsistentEntitiesOutsideIC relative="+INF" mean="0.03519368" deviation="0.09769048" sum="37379.91628798" squareSum="11451.80488335" numSamples="1062120" />
		<missingEntities relative="0.26471" mean="13.66006854" deviation="46.06668988" sum="14508632" squareSum="2.45215616e9" numSamples="1062120" />
		<overAccountedEntities relative="-0.04465" mean="6.54340188" deviation="29.2194394" sum="6949878" squareSum="952288026" numSamples="1062120" />
	</capture>
	<capture class="Plane (-0.00575, 0.00748, 0.035)">
		<omega relative="0.56456" mean="0.03721688" deviation="0.23363905" sum="39528.78775409" squareSum="59449.30128358" numSamples="1062120" />
		<inconsistency relative="0.38684" mean="0.00783422" deviation="0.03024518" sum="8320.88336825" squareSum="1036.78432738" numSamples="1062120" />
		<icSize relative="-0.37515" mean="4.7985463" deviation="11.82099154" sum="5096632" squareSum="172872656" numSamples="1062120" />
		<entitiesInInconsistentArea relative="-INF" mean="76.51864479" deviation="188.78325413" sum="81271983" squareSum="4.4071841e10" numSamples="1062120" />
		<entitiesInSDS relative="-INF" mean="489.33345761" deviation="511.08786359" sum="519730852" squareSum="5.31758914e11" numSamples="1062120" />
		<inconsistencyProbability relative="0.40762" mean="0.31114497" deviation="0.37352102" sum="330473.29353451" squareSum="251009.91326049" numSamples="1062120" />
		<inconsistentEntitiesOutsideIC relative="+INF" mean="0.03519368" deviation="0.09769048" sum="37379.91628798" squareSum="11451.80488335" numSamples="1062120" />
		<missingEntities relative="-0.71737" mean="9.34513614" deviation="29.99839234" sum="9925656" squareSum="1048562158" numSamples="1062120" />
		<overAccountedEntities relative="0.51805" mean="13.56056001" deviation="53.53609662" sum="14402942" squareSum="3.23946858e9" numSamples="1062120" />
	</capture>
	<capture class="Orthographic (depth&gt;extent)_ExPC">
		<omega relative="0.13924" mean="0.02662613" deviation="0.21576963" sum="28280.14085257" squareSum="50201.61685259" numSamples="1062120" />
		<inconsistency relative="0.09458" mean="0.00652267" deviation="0.02798754" sum="6927.85638657" squareSum="877.1494349" numSamples="1062120" />
		<icSize relative="-0.37515" mean="4.7985463" deviation="11.82099154" sum="5096632" squareSum="172872656" numSamples="1062120" />
		<entitiesInInconsistentArea relative="-INF" mean="76.51864479" deviation="188.78325413" sum="81271983" squareSum="4.4071841e10" numSamples="1062120" />
		<entitiesInSDS relative="-INF" mean="489.33345761" deviation="511.08786359" sum="519730852" squareSum="5.31758914e11" numSamples="1062120" />
		<inconsistencyProbability relative="0.19394" mean="0.29209158" deviation="0.3637546" sum="310236.30452319" squareSum="231154.37953452" numSamples="1062120" />
		<inconsistentEntitiesOutsideIC relative="+INF" mean="0.03519368" deviation="0.09769048" sum="37379.91628798" squareSum="11451.80488335" numSamples="1062120" />
		<missingEntities relative="0.22507" mean="13.48590178" deviation="45.69820899" sum="14323646" squareSum="2.41122042e9" numSamples="1062120" />
		<overAccountedEntities relative="-0.0263" mean="6.77231857" deviation="29.62372052" sum="7193015" squareSum="980792533" numSamples="1062120" />
	</capture>
</xml>
